xmldirector.connector-0.2.4.5-py3.7-nspkg.pth
xmldirector/connector/__init__.py
xmldirector/connector/configure.zcml
xmldirector/connector/connector.py
xmldirector/connector/header.txt
xmldirector/connector/i18n.py
xmldirector/connector/interfaces.py
xmldirector/connector/logger.py
xmldirector/connector/meta.zcml
xmldirector/connector/profiles.zcml
xmldirector/connector/browser/__init__.py
xmldirector/connector/browser/configure.zcml
xmldirector/connector/browser/connector.py
xmldirector/connector/browser/connector_highlight.pt
xmldirector/connector/browser/connector_inline.pt
xmldirector/connector/browser/connector_view.pt
xmldirector/connector/browser/controlpanel.py
xmldirector/connector/browser/resources/clipboard.min.js
xmldirector/connector/browser/resources/connector.js
xmldirector/connector/browser/resources/dropzone.css
xmldirector/connector/browser/resources/dropzone.js
xmldirector/connector/browser/resources/dropzone_basic.css
xmldirector/connector/browser/resources/jquery.blockUI.js
xmldirector/connector/browser/resources/jquery.spin.tar
xmldirector/connector/browser/resources/moment-with-locales.js
xmldirector/connector/browser/resources/run_prettify.js
xmldirector/connector/browser/resources/styles.css
xmldirector/connector/browser/resources/tabulator.min.css
xmldirector/connector/browser/resources/tabulator.min.js
xmldirector/connector/browser/resources/images/cancel.svg
xmldirector/connector/browser/resources/images/connector_icon.png
xmldirector/connector/browser/resources/images/directory.svg
xmldirector/connector/browser/resources/images/download.png
xmldirector/connector/browser/resources/images/edit.png
xmldirector/connector/browser/resources/images/eye.png
xmldirector/connector/browser/resources/images/reload.svg
xmldirector/connector/browser/resources/images/remove.png
xmldirector/connector/browser/resources/images/rename.png
xmldirector/connector/browser/resources/images/spinning.gif
xmldirector/connector/browser/resources/images/zip.png
xmldirector.connector-0.2.4.5.dist-info/METADATA
xmldirector.connector-0.2.4.5.dist-info/WHEEL
xmldirector.connector-0.2.4.5.dist-info/entry_points.txt
xmldirector.connector-0.2.4.5.dist-info/namespace_packages.txt
xmldirector.connector-0.2.4.5.dist-info/top_level.txt
xmldirector.connector-0.2.4.5.dist-info/RECORD
