Metadata-Version: 2.1
Name: xmldirector.connector
Version: 0.2.4.5
Summary: xmldirector.connector supports mounting storages like S3, Webdav backend or local filesystem into Plone
Home-page: http://pypi.python.org/pypi/xmldirector.connector
Author: Andreas Jung
Author-email: info@zopyx.com
License: GPL
Keywords: XML Director exist-db basex owncloud alfresco existdb Plone XML Python WebDAV
Platform: UNKNOWN
Classifier: Programming Language :: Python
Classifier: Programming Language :: Python :: 2.7
Classifier: Programming Language :: Python :: 3.6
Classifier: Programming Language :: Python :: 3.7
Classifier: Framework :: Plone
Classifier: Framework :: Plone :: 5.1
Classifier: Framework :: Plone :: 5.2
Classifier: Framework :: Zope2
Classifier: Topic :: Software Development :: Libraries :: Python Modules
Requires-Dist: setuptools
Requires-Dist: zope.i18nmessageid
Requires-Dist: plone.browserlayer
Requires-Dist: furl
Requires-Dist: fs (>=2.1)
Requires-Dist: fs.webdavfs
Requires-Dist: plone.app.testing
Requires-Dist: defusedxml
Requires-Dist: plone.api
